CHANGELOG.md
LICENSE
README.md
REFERENCE.md
encoderwheel/__init__.py
encoderwheel/is31fl3731.py
pimoroni_encoderwheel-0.0.1.dist-info/METADATA
pimoroni_encoderwheel-0.0.1.dist-info/WHEEL
pimoroni_encoderwheel-0.0.1.dist-info/licenses/LICENSE
pimoroni_encoderwheel-0.0.1.dist-info/RECORD
